<launch>

  <include file="$(find-pkg-share common_sensor_launch)/launch/dummy_diag_publisher/septentrio.launch.xml"/>
  <include file="$(find-pkg-share aip_x2_launch)/launch/dummy_diag_publisher/lidar.launch.xml"/>

  <include file="$(find-pkg-share dummy_diag_publisher)/launch/dummy_diag_publisher_node.launch.xml">
    <arg name="diag_name" value="sensing_topic_status"/>
  </include>

  <include file="$(find-pkg-share dummy_diag_publisher)/launch/dummy_diag_publisher_node.launch.xml">
    <arg name="diag_name" value="concat_status"/>
  </include>

  <include file="$(find-pkg-share dummy_diag_publisher)/launch/dummy_diag_publisher_node.launch.xml">
    <arg name="diag_name" value="temperature_status"/>
  </include>

</launch>
